sss_jupyter/__init__.py
sss_jupyter/__main__.py
sss_jupyter/cli.py
sss_jupyter/launch.sh
sss_jupyter-0.0.1.dist-info/METADATA
sss_jupyter-0.0.1.dist-info/WHEEL
sss_jupyter-0.0.1.dist-info/entry_points.txt
sss_jupyter-0.0.1.dist-info/licenses/LICENSE
sss_jupyter-0.0.1.dist-info/RECORD
