Metadata-Version: 2.1
Name: sss-jupyter
Version: 0.0.1
Summary: Python package to launch a self-signed SSL JupyterLab server
Project-URL: Homepage, https://github.com/omitakahiro/sss-jupyter
Project-URL: Repository, https://github.com/omitakahiro/sss-jupyter.git
Author: Takahiro Omi
License: MIT License
License-File: LICENSE
Classifier: Programming Language :: Python
Requires-Python: >=3.7
Requires-Dist: jupyterlab
